papylon/arbitrary.py
papylon/checker.py
papylon/gen.py
papylon/printer.py
papylon/prop.py
papylon/shrinker.py
papylon/utils.py
papylon/__init__.py
papylon-0.6.1.dist-info/DESCRIPTION.rst
papylon-0.6.1.dist-info/METADATA
papylon-0.6.1.dist-info/metadata.json
papylon-0.6.1.dist-info/RECORD
papylon-0.6.1.dist-info/top_level.txt
papylon-0.6.1.dist-info/WHEEL
tests/test_arbitrary.py
tests/test_checker.py
tests/test_gen.py
tests/test_prop.py
tests/test_shrinker.py
tests/test_utils.py
tests/__init__.py
