Metadata-Version: 2.0
Name: papylon
Version: 0.6.1
Summary: Random testing for Python
Home-page: https://github.com/Gab-km/papylon
Author: Kazuhiro Matsushima
Author-email: the25thcromosome@gmail.com
License: The MIT License (MIT)
Keywords: papylon quickcheck random test
Platform: UNKNOWN
Classifier: Development Status :: 4 - Beta
Classifier: Intended Audience :: Developers
Classifier: License :: OSI Approved :: MIT License
Classifier: Programming Language :: Python
Classifier: Programming Language :: Python :: 3.3
Classifier: Programming Language :: Python :: 3.4
Classifier: Programming Language :: Python :: 3.5
Classifier: Topic :: Software Development :: Libraries
Classifier: Topic :: Software Development :: Testing
Classifier: Topic :: Utilities
Requires-Dist: setuptools
